qualesim_sisq/__init__.py
qualesim_sisq/__main__.py
qualesim_sisq/frontend.py
qualesim_sisq/utils.py
qualesim_sisq-1.1.0.data/data/bin/dqcsfesisq
qualesim_sisq-1.1.0.dist-info/LICENSE
qualesim_sisq-1.1.0.dist-info/METADATA
qualesim_sisq-1.1.0.dist-info/WHEEL
qualesim_sisq-1.1.0.dist-info/top_level.txt
qualesim_sisq-1.1.0.dist-info/RECORD
