Metadata-Version: 2.1
Name: qualesim-sisq
Version: 1.1.0
Summary: QuaLeSim frontend for SISQ.
Home-page: https://gitee.com/hpcl_quanta/dqcsim-sisq.git
Author: Dingdong Liu
Author-email: dingdongliu@quanta.org.cn
License: GPLv3
Keywords: qualesim sisq
Classifier: Development Status :: 3 - Alpha
Classifier: Intended Audience :: Science/Research
Classifier: License :: OSI Approved :: GNU General Public License v3 (GPLv3)
Classifier: Topic :: Scientific/Engineering
License-File: LICENSE
Requires-Dist: numpy
Requires-Dist: ply
Requires-Dist: sisq
